[
 {
  "file": "audi-a5-s-line-s5-2017-2024-bonnet-hood-panel-8w68230.webp",
  "title": "Audi A5 S Line S5 2017-2024 Bonnet Hood Panel / 8W6823029",
  "brand": "Audi"
 },
 {
  "file": "mercedes-benz-a-class-w177-2019-2022-amg-front-bumper-with-g.webp",
  "title": "Mercedes-Benz A Class W177 2019\u20132022 AMG Front Bumper with GT Grille",
  "brand": "Mercedes-Benz"
 },
 {
  "file": "mercedes-benz-a-class-w176-2016-2018-amg-a45-front-bumper-wi.webp",
  "title": "Mercedes-Benz A Class W176 2016\u20132018 AMG A45 Front Bumper with Diamond Grille",
  "brand": "Mercedes-Benz"
 },
 {
  "file": "bmw-3-series-g20-lci-2023-onwards-front-bumper-trims.webp",
  "title": "BMW 3 Series G20 LCI 2023 Onwards Front Bumper Trims / M Sport / M340",
  "brand": "BMW"
 },
 {
  "file": "lexus-ct200h-2014-2020-front-bumper-radiator-grille-f.webp",
  "title": "Lexus CT200h 2014-2020 Front Bumper Radiator Grille / F Sport 2021 Look",
  "brand": "Lexus"
 },
 {
  "file": "audi-q5-s-line-2021-2024-front-bumper-undertray-cover.webp",
  "title": "Audi Q5 S-Line 2021\u20132024 Front Bumper Undertray Cover",
  "brand": "Audi"
 },
 {
  "file": "audi-a4-b9-5-2020-2024-front-bumper-undertray-cover-8.webp",
  "title": "Audi A4 B9.5 2020\u20132024 Front Bumper Undertray Cover / 8WD807611C",
  "brand": "Audi"
 },
 {
  "file": "lexus-nx350h-2022-2026-front-right-wing-arch-moulding.webp",
  "title": "Lexus NX350h 2022-2026 Front Right Wing Arch Moulding Trim / Driver Side",
  "brand": "Lexus"
 },
 {
  "file": "bmw-x3-g01-x4-g02-2018-2021-front-left-led-fog-light.webp",
  "title": "BMW X3 G01 X4 G02 2018-2021 Front Left LED Fog Light Lamp / Passenger Side",
  "brand": "BMW"
 },
 {
  "file": "lexus-rx450-2013-2015-front-right-headlight-bracket-dr.webp",
  "title": "Lexus RX450 2013-2015 Front Right Headlight Bracket / Driver Side / 52134-48040",
  "brand": "Lexus"
 },
 {
  "file": "mercedes-benz-cla-class-c118-2019-2023-front-radar-sensor-mo.webp",
  "title": "Mercedes-Benz CLA Class C118 2019-2023 Front Radar Sensor Mount Bracket",
  "brand": "Mercedes-Benz"
 },
 {
  "file": "volkswagen-golf-8-r-line-2020-2023-front-bumper-with-grille.webp",
  "title": "Volkswagen Golf 8 R-Line 2020\u20132023 Front Bumper With Grilles / Grey",
  "brand": "Volkswagen"
 },
 {
  "file": "toyota-hilux-2019-on-front-bumper-with-grilles-and-fog.webp",
  "title": "Toyota Hilux 2019-On Front Bumper with Grilles and Fog Lights / Navy Blue",
  "brand": "Toyota"
 },
 {
  "file": "toyota-hilux-2019-on-genuine-complete-front-bumper-with.webp",
  "title": "Toyota Hilux 2019-On Genuine Complete Front Bumper with Grille | 52119-\u20180KK00",
  "brand": "Toyota"
 },
 {
  "file": "volkswagen-golf-7-5-gti-2017-2019-complete-front-bumper-wit.webp",
  "title": "Volkswagen Golf 7.5 GTI 2017-2019 Complete Front Bumper with Grilles",
  "brand": "Volkswagen"
 },
 {
  "file": "toyota-rav4-2018-2024-front-right-lower-door-moulding-t.webp",
  "title": "Toyota Rav4 2018-2024 Front Right Lower Door Moulding Trim / Drivers Side",
  "brand": "Toyota"
 }
]